{"file_suffix": ".fjson", "theme_includehidden": "True", "rellinks": [["genindex", "General Index", "I", "index"]], "html5_doctype": null, "sourcelink_suffix": ".txt", "theme_style_external_links": "False", "master_doc": "index", "theme_analytics_id": "", "style": "css/theme.css", "theme_display_version": "True", "copyright": "2020, An Pham", "show_copyright": true, "version": "", "parents": [], "theme_titles_only": "", "shorttitle": "Build DevOps Stack  documentation", "theme_navigation_with_keys": "False", "css_files": [], "script_files": ["_static/jquery.js", "_static/underscore.js", "_static/doctools.js", "_static/language_data.js"], "theme_body_max_width": "800", "use_opensearch": "", "embedded": false, "theme_collapse_navigation": "True", "project": "Build DevOps Stack", "theme_body_min_width": "450", "release": "", "has_source": true, "show_sphinx": true, "last_updated": null, "theme_nosidebar": "false", "favicon": "", "logo": "", "theme_sticky_navigation": "True", "show_source": true, "docstitle": "Build DevOps Stack  documentation", "theme_navigation_depth": "4", "theme_canonical_url": "", "language": null, "builder": "json", "theme_prev_next_buttons_location": "bottom", "theme_style_nav_header_background": "", "theme_sidebarwidth": "230", "sphinx_version": "1.8.5", "theme_logo_only": ""}